milvus/__init__.py
milvus/settings.py
milvus/client/__init__.py
milvus/client/abstract.py
milvus/client/asynch.py
milvus/client/check.py
milvus/client/client_hooks.py
milvus/client/exceptions.py
milvus/client/grpc_handler.py
milvus/client/http_handler.py
milvus/client/pool.py
milvus/client/prepare.py
milvus/client/stub.py
milvus/client/types.py
milvus/client/utils.py
milvus/client/hooks/__init__.py
milvus/client/hooks/abstract.py
milvus/grpc_gen/__init__.py
milvus/grpc_gen/milvus_pb2.py
milvus/grpc_gen/milvus_pb2_grpc.py
milvus/grpc_gen/status_pb2.py
milvus/grpc_gen/status_pb2_grpc.py
milvus_one-1.1.3.dev0.dist-info/LICENSE
milvus_one-1.1.3.dev0.dist-info/METADATA
milvus_one-1.1.3.dev0.dist-info/WHEEL
milvus_one-1.1.3.dev0.dist-info/top_level.txt
milvus_one-1.1.3.dev0.dist-info/RECORD
