Metadata-Version: 2.1
Name: milvus-one
Version: 1.1.3.dev0
Summary: Python Sdk for Milvus
Home-page: https://github.com/milvus-io/pymilvus
Author: Milvus Team
Author-email: milvus-team@zilliz.com
License: Apache-2.0
Classifier: Programming Language :: Python :: 3.6
Classifier: Programming Language :: Python :: 3.7
Classifier: Programming Language :: Python :: 3.8
Requires-Python: >=3.6
License-File: LICENSE
Requires-Dist: grpcio (<1.38.0,>=1.22.0)
Requires-Dist: grpcio-tools (<1.38.0,>=1.22.0)
Requires-Dist: requests (>=2.22.0)
Requires-Dist: ujson (>=2.0.0)
